{
	"username": "natgeo",
	"profileUrl": "https://www.instagram.com/natgeo/",
	"followersCount": 277,
	"followsCount": 0,
	"bio": "30,810 posts\n277M followers\n171 following",
	"posts": [
		{
			"postUrl": "https://www.instagram.com/natgeo/reel/DMNbY-TRBlZ/",
			"caption": "With cutting-edge science on his side, @chrishemsworth is back and ready to journey to the edge of his comfort zone—and learn how we can all live better.\n\nSeason 2 of #LimitlessWithChrisHemsworth premieres August 15 on @DisneyPlus and @hulu. Season 1 is now streaming.",
			"likesCount": null,
			"commentsCount": null
		},
		{
			"postUrl": "https://www.instagram.com/natgeo/p/DN39r1Fj7_J/",
			"caption": "Photo by National Geographic on August 27, 2025. May be an image of tick, isopod, cockroach and text that says \"What to know about lice and how it spreads\".",
			"likesCount": null,
			"commentsCount": null
		},
		{
			"postUrl": "https://www.instagram.com/natgeo/p/DN3pFkhXm74/",
			"caption": "Photo by National Geographic on August 27, 2025. May be an image of frog, reptile and text.",
			"likesCount": null,
			"commentsCount": null
		},
		{
			"postUrl": "https://www.instagram.com/natgeo/p/DN3Unp3ZtAH/",
			"caption": "@chrishemsworth got every question from @drmayashankar right. How did you do? 🧠\n\n#LimitlessWithChrisHemsworth is now streaming on @DisneyPlus and @hulu.",
			"likesCount": null,
			"commentsCount": null
		},
		{
			"postUrl": "https://www.instagram.com/natgeo/p/DN25GVB0idF/",
			"caption": "Photo by National Geographic on August 27, 2025. May be an image of 8 people, Fushimi Inari Taisha and text.",
			"likesCount": null,
			"commentsCount": null
		}
	],
	"relatedProfiles": [],
	"highlightReel": [
		"30,810 posts",
		"30,810",
		"30,810",
		"277M followers",
		"277M",
		"277M",
		"171 following",
		"171",
		"171",
		"Limitless",
		"Limitless",
		"Penguins",
		"Penguins",
		"Underdogs",
		"Underdogs",
		"Nat Geo 33",
		"Nat Geo 33",
		"POY 2024",
		"POY 2024",
		"BOTW 2025",
		"BOTW 2025",
		"9GAG: Go Fun The World",
		"BBC News",
		"NPR",
		"National Park Service",
		"The New Yorker",
		"National Geographic Your Shot",
		"Vogue",
		"Animals Doing Things",
		"The Tonight Show",
		"Red Bull",
		"Discover Earth",
		"The Economist",
		"Betches Media",
		"Nature Is Metal",
		"Miley Cyrus",
		"The Guardian",
		"LADbible",
		"Saturday Night Live",
		"Rolling Stone",
		"SHIT YOU SHOULD CARE ABOUT",
		"Ocean Destinations",
		"Reuters",
		"Banksy",
		"Disney",
		"THE GOOD FILMS",
		"Today Years Old",
		"Pictoline",
		"Coldplay",
		"Mel Robbins",
		"Natural Habitat Shorts",
		"LEGO",
		"Galaxies",
		"Ed Sheeran",
		"Doggos Doing Things",
		"BeigeCardigan",
		"Christian Watson | 1924us",
		"BBC News Mundo",
		"Pixar",
		"Middle Class Fancy",
		"Diet Prada ™",
		"Humans of New York",
		"National Audubon Society",
		"World Wildlife Fund",
		"Justin Bieber",
		"Ami Vitale",
		"SEASPIRACY",
		"Outside Magazine",
		"New Scientist",
		"U.S. Fish and Wildlife Service",
		"433",
		"Whales Nation",
		"Sabrina Carpenter",
		"Animal Planet India",
		"VICE",
		"The Associated Press (AP)",
		"Strange Planet",
		"SportsCenter",
		"Leonardo DiCaprio",
		"Travel + Leisure",
		"National Geographic España",
		"Millie Bobby Brown",
		"NBA",
		"The Atlantic",
		"UN Environment Programme",
		"UFC",
		"ACLU",
		"WIRED",
		"Premier League",
		"Charles Leclerc",
		"Interesting Engineering",
		"BBC",
		"Brian Skerry",
		"Sociaty",
		"Nugget",
		"Venue Earth 🌍🌎🌏",
		"Cats Doing Things",
		"Stephen Wilkes",
		"Fboy Problems",
		"Marvel Entertainment",
		"Scuderia Ferrari HP"
	]
}